<?xml version="1.0" encoding="utf-8"?>
<savedqueries xmlns:xsi="http://www.w3.org/2001/XMLSchema-instance">
  <savedquery>
    <IsCustomizable>1</IsCustomizable>
    <CanBeDeleted>0</CanBeDeleted>
    <isquickfindquery>0</isquickfindquery>
    <isprivate>0</isprivate>
    <isdefault>1</isdefault>
    <savedqueryid>{46ea2aa0-1c3c-4687-b415-538aa92c41ba}</savedqueryid>
    <layoutxml>
      <grid name="ppalm_jobdescriptions" jump="ppalm_id" select="1" icon="1" preview="1">
        <row name="ppalm_jobdescription" id="ppalm_jobdescriptionid">
          <cell name="ppalm_id" width="300" />
          <cell name="createdon" width="125" />
        </row>
      </grid>
    </layoutxml>
    <querytype>2</querytype>
    <fetchxml>
      <fetch version="1.0" mapping="logical">
        <entity name="ppalm_jobdescription">
          <attribute name="ppalm_jobdescriptionid" />
          <attribute name="ppalm_id" />
          <attribute name="createdon" />
          <order attribute="ppalm_id" descending="false" />
          <filter type="and">
            <condition attribute="statecode" operator="eq" value="0" />
          </filter>
        </entity>
      </fetch>
    </fetchxml>
    <IntroducedVersion>1.0</IntroducedVersion>
    <LocalizedNames>
      <LocalizedName description="JobDescription Associated View" languagecode="1033" />
    </LocalizedNames>
  </savedquery>
</savedqueries>